MANIFEST.in
README
README.md
setup.cfg
setup.py
modularity/__init__.py
modularity/modularity.py
modularity.egg-info/PKG-INFO
modularity.egg-info/SOURCES.txt
modularity.egg-info/dependency_links.txt
modularity.egg-info/top_level.txt