Metadata-Version: 1.0
Name: modularity
Version: 0.0.2
Summary: A library for managing dynamic modules.
Home-page: https://github.com/csu/modularity
Author: Christopher Su
Author-email: chris+py@christopher.su
License: UNKNOWN
Platform: UNKNOWN
